MANIFEST.in
README
setup.py
pitz/__init__.py
pitz/bag.py
pitz/jquery-1.3.2.min.js
pitz/logging.cfg
pitz/project.py
pitz.egg-info/PKG-INFO
pitz.egg-info/SOURCES.txt
pitz.egg-info/dependency_links.txt
pitz.egg-info/entry_points.txt
pitz.egg-info/not-zip-safe
pitz.egg-info/requires.txt
pitz.egg-info/top_level.txt
pitz/cmdline/__init__.py
pitz/cmdline/pitzaddtag.py
pitz/cmdline/pitzcomment.py
pitz/cmdline/pitzedit.py
pitz/cmdline/pitzsetup.py
pitz/cmdline/webapp.py
pitz/entity/__init__.py
pitz/entity/person.py
pitz/entity/task.py
pitz/jinja2templates/__init__.py
pitz/jinja2templates/bag.html
pitz/jinja2templates/bag_detailed_view.txt
pitz/jinja2templates/bag_rst_detailed_view.txt
pitz/jinja2templates/base.html
pitz/jinja2templates/by_owner_view.txt
pitz/jinja2templates/colorized_bag_detailed_view.txt
pitz/jinja2templates/colorized_by_owner_view.txt
pitz/jinja2templates/colorized_description_view.txt
pitz/jinja2templates/colorized_task_detailed_view.txt
pitz/jinja2templates/colorized_task_summarized_view.txt
pitz/jinja2templates/comment_detailed_view.txt
pitz/jinja2templates/comment_summarized_view.txt
pitz/jinja2templates/component.html
pitz/jinja2templates/description_view.txt
pitz/jinja2templates/entity.html
pitz/jinja2templates/entity_attributes_table.txt
pitz/jinja2templates/entity_detailed_view.txt
pitz/jinja2templates/entity_verbose_view.txt
pitz/jinja2templates/estimate.html
pitz/jinja2templates/footer.html
pitz/jinja2templates/help.html
pitz/jinja2templates/macros.html
pitz/jinja2templates/milestone.html
pitz/jinja2templates/person.html
pitz/jinja2templates/pitz_todo.txt
pitz/jinja2templates/project.html
pitz/jinja2templates/silly.html
pitz/jinja2templates/status.html
pitz/jinja2templates/tag.html
pitz/jinja2templates/task-edit-attributes.html
pitz/jinja2templates/task.html
pitz/jinja2templates/task_activity_view.txt
pitz/jinja2templates/task_comments_view.txt
pitz/jinja2templates/task_detailed_view.txt
pitz/jinja2templates/task_rst_detailed_view.txt
pitz/jinja2templates/task_rst_summarized_view.txt
pitz/jinja2templates/task_summarized_view.txt
pitz/jinja2templates/task_verbose_view.txt
pitz/jinja2templates/team.html
pitz/jinja2templates/update_task.html
