Metadata-Version: 1.0
Name: pitz
Version: 1.2.4
Summary: Python to-do tracker inspired by ditz (ditz.rubyforge.org)
Home-page: http://pitz.tplus1.com
Author: Matt Wilson
Author-email: matt@tplus1.com
License: BSD
Keywords: ditz
Platform: UNKNOWN
